phpthon/__init__.py
phpthon/phpthon.py
phpthon-1.1.dist-info/METADATA
phpthon-1.1.dist-info/WHEEL
phpthon-1.1.dist-info/top_level.txt
phpthon-1.1.dist-info/RECORD
